<annotation>
	<folder />
	<filename>001f581f2f2db648_jpg.rf.58c53483b743dc608c8501c23b6cc8c9.jpg</filename>
	<path>001f581f2f2db648_jpg.rf.58c53483b743dc608c8501c23b6cc8c9.jpg</path>
	<source>
		<database>roboflow.ai</database>
	</source>
	<size>
		<width>640</width>
		<height>480</height>
		<depth>3</depth>
	</size>
	<segmented>0</segmented>
	<object>
		<name>Mobile-phone</name>
		<pose>Unspecified</pose>
		<truncated>0</truncated>
		<difficult>0</difficult>
		<occluded>0</occluded>
		<bndbox>
			<xmin>283</xmin>
			<xmax>411</xmax>
			<ymin>109</ymin>
			<ymax>234</ymax>
		</bndbox>
	</object>
	<object>
		<name>Mobile-phone</name>
		<pose>Unspecified</pose>
		<truncated>0</truncated>
		<difficult>0</difficult>
		<occluded>0</occluded>
		<bndbox>
			<xmin>380</xmin>
			<xmax>454</xmax>
			<ymin>249</ymin>
			<ymax>320</ymax>
		</bndbox>
	</object>
	<object>
		<name>Mobile-phone</name>
		<pose>Unspecified</pose>
		<truncated>0</truncated>
		<difficult>0</difficult>
		<occluded>0</occluded>
		<bndbox>
			<xmin>470</xmin>
			<xmax>522</xmax>
			<ymin>257</ymin>
			<ymax>311</ymax>
		</bndbox>
	</object>
</annotation>