<annotation>
	<folder />
	<filename>88c2a91f4baafbd4_jpg.rf.fbfd0facfe82bb094439a57b46730b5e.jpg</filename>
	<path>88c2a91f4baafbd4_jpg.rf.fbfd0facfe82bb094439a57b46730b5e.jpg</path>
	<source>
		<database>roboflow.ai</database>
	</source>
	<size>
		<width>640</width>
		<height>480</height>
		<depth>3</depth>
	</size>
	<segmented>0</segmented>
	<object>
		<name>Mobile-phone</name>
		<pose>Unspecified</pose>
		<truncated>0</truncated>
		<difficult>0</difficult>
		<occluded>0</occluded>
		<bndbox>
			<xmin>1</xmin>
			<xmax>637</xmax>
			<ymin>1</ymin>
			<ymax>481</ymax>
		</bndbox>
	</object>
</annotation>