<annotation>
	<folder />
	<filename>db3bdd5768bc19f4_jpg.rf.f81651c18e9ce899bae0dc1f80f7490f.jpg</filename>
	<path>db3bdd5768bc19f4_jpg.rf.f81651c18e9ce899bae0dc1f80f7490f.jpg</path>
	<source>
		<database>roboflow.ai</database>
	</source>
	<size>
		<width>640</width>
		<height>480</height>
		<depth>3</depth>
	</size>
	<segmented>0</segmented>
	<object>
		<name>Watch</name>
		<pose>Unspecified</pose>
		<truncated>0</truncated>
		<difficult>0</difficult>
		<occluded>0</occluded>
		<bndbox>
			<xmin>175</xmin>
			<xmax>438</xmax>
			<ymin>1</ymin>
			<ymax>480</ymax>
		</bndbox>
	</object>
</annotation>